ezduckdb/__init__.py
ezduckdb/core.py
ezduckdb/paths.py
ezduckdb-0.0.8.dist-info/LICENSE
ezduckdb-0.0.8.dist-info/METADATA
ezduckdb-0.0.8.dist-info/WHEEL
ezduckdb-0.0.8.dist-info/top_level.txt
ezduckdb-0.0.8.dist-info/RECORD
